consent/__init__.py
consent/apps.py
consent/errors.py
consent/helpers.py
consent/mixins.py
consent/models.py
consent/urls.py
consent/admin/__init__.py
consent/api/__init__.py
consent/api/permissions.py
consent/api/urls.py
consent/api/v1/__init__.py
consent/api/v1/urls.py
consent/api/v1/views.py
consent/migrations/0001_initial.py
consent/migrations/0002_migrate_to_new_data_sharing_consent.py
consent/migrations/0003_historicaldatasharingconsent_history_change_reason.py
consent/migrations/0004_datasharingconsenttextoverrides.py
consent/migrations/0005_auto_20230707_0755.py
consent/migrations/0006_alter_historicaldatasharingconsent_options.py
consent/migrations/0007_datasharingconsent_consent_add_username_index.py
consent/migrations/__init__.py
edx_enterprise-6.6.2.dist-info/licenses/LICENSE
enterprise/__init__.py
enterprise/apps.py
enterprise/cache_utils.py
enterprise/constants.py
enterprise/decorators.py
enterprise/errors.py
enterprise/event_bus.py
enterprise/forms.py
enterprise/logging.py
enterprise/messages.py
enterprise/middleware.py
enterprise/models.py
enterprise/roles_api.py
enterprise/rules.py
enterprise/signals.py
enterprise/tasks.py
enterprise/toggles.py
enterprise/tpa_pipeline.py
enterprise/urls.py
enterprise/utils.py
enterprise/validators.py
enterprise/views.py
enterprise/views_error_codes.txt
enterprise/admin/__init__.py
enterprise/admin/actions.py
enterprise/admin/forms.py
enterprise/admin/paginator.py
enterprise/admin/utils.py
enterprise/admin/views.py
enterprise/admin/widgets.py
enterprise/api/__init__.py
enterprise/api/filters.py
enterprise/api/pagination.py
enterprise/api/throttles.py
enterprise/api/urls.py
enterprise/api/utils.py
enterprise/api/v1/__init__.py
enterprise/api/v1/decorators.py
enterprise/api/v1/fields.py
enterprise/api/v1/permissions.py
enterprise/api/v1/serializers.py
enterprise/api/v1/urls.py
enterprise/api/v1/views/__init__.py
enterprise/api/v1/views/analytics_summary.py
enterprise/api/v1/views/base_views.py
enterprise/api/v1/views/coupon_codes.py
edx_enterprise-6.6.2.dist-info/METADATA
edx_enterprise-6.6.2.dist-info/WHEEL
edx_enterprise-6.6.2.dist-info/top_level.txt
edx_enterprise-6.6.2.dist-info/RECORD
