Metadata-Version: 2.4
Name: edx-enterprise
Version: 6.6.2
Summary: Your project description goes here
Home-page: https://github.com/openedx/edx-enterprise
Author: edX
Author-email: oscm@edx.org
License: AGPL 3.0
Keywords: Django edx
Classifier: Development Status :: 3 - Alpha
Classifier: Framework :: Django
Classifier: Framework :: Django :: 4.2
Classifier: Framework :: Django :: 5.2
Classifier: Intended Audience :: Developers
Classifier: License :: OSI Approved :: GNU Affero General Public License v3 or later (AGPLv3+)
Classifier: Natural Language :: English
Classifier: Programming Language :: Python :: 3
Classifier: Programming Language :: Python :: 3.11
License-File: LICENSE
Requires-Dist: bleach
Requires-Dist: celery
Requires-Dist: code-annotations
Requires-Dist: cryptography
Requires-Dist: django-cache-memoize
Requires-Dist: django-config-models
Requires-Dist: django-countries
Requires-Dist: django-crum
Requires-Dist: django-fernet-fields-v2
Requires-Dist: django-filter
Requires-Dist: django-ipware
Requires-Dist: django-model-utils
Requires-Dist: django-multi-email-field
Requires-Dist: django-object-actions
Requires-Dist: django-simple-history
Requires-Dist: django-waffle
Requires-Dist: django
Requires-Dist: djangorestframework-xml
Requires-Dist: djangorestframework
Requires-Dist: edx-django-utils>=3.12.0
Requires-Dist: edx-drf-extensions
Requires-Dist: edx-opaque-keys[django]
Requires-Dist: edx-rest-api-client
Requires-Dist: edx-rbac
Requires-Dist: tincan
Requires-Dist: edx-toggles
Requires-Dist: jsondiff
Requires-Dist: jsonfield
Requires-Dist: openedx-atlas
Requires-Dist: openedx-events
Requires-Dist: paramiko
Requires-Dist: path.py
Requires-Dist: pillow
Requires-Dist: python-dateutil
Requires-Dist: pytz
Requires-Dist: requests
Requires-Dist: rules
Requires-Dist: slumber
Requires-Dist: snowflake-connector-python
Requires-Dist: stevedore
Requires-Dist: testfixtures
Requires-Dist: unicodecsv
Requires-Dist: PGPy
Requires-Dist: django-oauth-toolkit
Provides-Extra: braze
Requires-Dist: edx-braze-client; extra == "braze"
Dynamic: author
Dynamic: author-email
Dynamic: classifier
Dynamic: description
Dynamic: home-page
Dynamic: keywords
Dynamic: license
Dynamic: license-file
Dynamic: provides-extra
Dynamic: requires-dist
Dynamic: summary
